audio_transcribing/__init__.py
audio_transcribing/natasha_stopwords_remover.py
audio_transcribing/transcriber.py
audio_transcribing/builders/__init__.py
audio_transcribing/builders/transcribe_processor_director.py
audio_transcribing/builders/voice_separator_director.py
audio_transcribing/interfaces/__init__.py
audio_transcribing/interfaces/istopwords_remover.py
audio_transcribing/interfaces/itranscribe_processor.py
audio_transcribing/interfaces/ivoice_separator.py
audio_transcribing/models/__init__.py
audio_transcribing/models/faster_whisper_processor.py
audio_transcribing/models/voice_separator.py
audio_transcribing/models/whisper_processor.py
audio_transcribing/utils/__init__.py
audio_transcribing/utils/audio_processing_mixin.py
audio_transcribing/utils/audio_segmenter.py
audio_transcribing-0.2.4.dist-info/licenses/LICENSE
audio_transcribing-0.2.4.dist-info/METADATA
audio_transcribing-0.2.4.dist-info/WHEEL
audio_transcribing-0.2.4.dist-info/top_level.txt
audio_transcribing-0.2.4.dist-info/RECORD
