Metadata-Version: 2.4
Name: audio_transcribing
Version: 0.2.4
Summary: A toolkit for audio transcription, speaker diarization, and text processing
Home-page: https://github.com/Lymuthien/transcriber-course-work
Author: Tatsiana Kozlova
Author-email: tanya126060@gmail.com
License: MIT
Classifier: Development Status :: 4 - Beta
Classifier: Intended Audience :: Developers
Classifier: License :: OSI Approved :: MIT License
Classifier: Programming Language :: Python :: 3.13
Classifier: Topic :: Software Development :: Libraries
Requires-Python: >=3.8
License-File: LICENSE
Requires-Dist: numpy>=1.21.0
Requires-Dist: soundfile>=0.10.3
Requires-Dist: torch>=1.10.0
Requires-Dist: faster-whisper>=1.0.0
Requires-Dist: pyannote.audio>=2.0.1
Requires-Dist: openai-whisper>=20240930
Requires-Dist: torchvision>=0.21.0
Requires-Dist: natasha>=1.6.0
Dynamic: author
Dynamic: author-email
Dynamic: classifier
Dynamic: description
Dynamic: description-content-type
Dynamic: home-page
Dynamic: license
Dynamic: license-file
Dynamic: requires-dist
Dynamic: requires-python
Dynamic: summary
